{
  "as_of": "2026-07-24",
  "source_timestamp": "July 24, 2026 5:00 AM",
  "games": [
    {
      "game_no": 586,
      "name": "25X THE CASH",
      "price": 10.0,
      "percent_unsold": 13.8,
      "total_unclaimed": 3061510.0,
      "top_prizes": [
        {
          "level": 10000,
          "remaining": 1
        },
        {
          "level": 5000,
          "remaining": 5
        },
        {
          "level": 1000,
          "remaining": 120
        },
        {
          "level": 500,
          "remaining": 116
        }
      ],
      "print_run": null,
      "remaining_tickets": null,
      "ev_per_ticket": null,
      "ev_ratio": null,
      "ev_ratio_adjusted": null,
      "relative_score": 221848.550725,
      "top_prize_odds_now": null,
      "dead_game": false,
      "flags": [
        "no_print_run"
      ],
      "confidence": "low",
      "value_score": null,
      "grade": null,
      "rated": false,
      "reason": "Print run unknown \u2014 expected value can't be computed; ranked by the relative unclaimed-money signal only.",
      "remaining_tickets_min": null,
      "remaining_tickets_max": null,
      "ev_ratio_min": null,
      "ev_ratio_max": null,
      "ev_scenarios": null,
      "overall_odds_launch": null
    },
    {
      "game_no": 617,
      "name": "HIGH ROLLER",
      "price": 5.0,
      "percent_unsold": 0.0,
      "total_unclaimed": 124025.0,
      "top_prizes": [
        {
          "level": 1000,
          "remaining": 2
        }
      ],
      "print_run": 1320000,
      "remaining_tickets": 0,
      "ev_per_ticket": null,
      "ev_ratio": null,
      "ev_ratio_adjusted": null,
      "relative_score": null,
      "top_prize_odds_now": null,
      "dead_game": true,
      "flags": [
        "sold_out"
      ],
      "confidence": "low",
      "value_score": null,
      "grade": null,
      "rated": false,
      "reason": "Top prize already claimed \u2014 the biggest advertised win can no longer be won.",
      "remaining_tickets_min": null,
      "remaining_tickets_max": null,
      "ev_ratio_min": null,
      "ev_ratio_max": null,
      "ev_scenarios": null,
      "overall_odds_launch": 3.82
    },
    {
      "game_no": 624,
      "name": "CASH BLAST",
      "price": 2.0,
      "percent_unsold": 0.3,
      "total_unclaimed": 80327.0,
      "top_prizes": [
        {
          "level": 10000,
          "remaining": 2
        },
        {
          "level": 1000,
          "remaining": 1
        }
      ],
      "print_run": 960000,
      "remaining_tickets": 2880,
      "ev_per_ticket": 27.891319,
      "ev_ratio": 13.94566,
      "ev_ratio_adjusted": null,
      "relative_score": 267756.666667,
      "top_prize_odds_now": 1440.0,
      "dead_game": false,
      "flags": [
        "anomaly_candidate",
        "ev_out_of_range",
        "low_inventory"
      ],
      "confidence": "low",
      "value_score": 40,
      "grade": "F",
      "rated": true,
      "reason": "Looks better than it is: most unclaimed prize money is likely on tickets already sold but not yet claimed (claim lag).",
      "remaining_tickets_min": 2400,
      "remaining_tickets_max": 3360,
      "ev_ratio_min": 11.953423,
      "ev_ratio_max": 16.734792,
      "ev_scenarios": [
        {
          "assumed_claimed_share": 0.5,
          "ev_ratio": 6.97283
        },
        {
          "assumed_claimed_share": 0.8,
          "ev_ratio": 2.789132
        },
        {
          "assumed_claimed_share": 0.95,
          "ev_ratio": 0.697283
        }
      ],
      "overall_odds_launch": 4.21
    },
    {
      "game_no": 630,
      "name": "$500,000 ROYAL CASH",
      "price": 20.0,
      "percent_unsold": 9.2,
      "total_unclaimed": 2743320.0,
      "top_prizes": [
        {
          "level": 500000,
          "remaining": 2
        },
        {
          "level": 10000,
          "remaining": 3
        },
        {
          "level": 5000,
          "remaining": 6
        },
        {
          "level": 1000,
          "remaining": 105
        },
        {
          "level": 500,
          "remaining": 280
        }
      ],
      "print_run": 960000,
      "remaining_tickets": 88320,
      "ev_per_ticket": 31.061141,
      "ev_ratio": 1.553057,
      "ev_ratio_adjusted": null,
      "relative_score": 298186.956522,
      "top_prize_odds_now": 44160.0,
      "dead_game": false,
      "flags": [
        "anomaly_candidate",
        "ev_out_of_range"
      ],
      "confidence": "low",
      "value_score": 40,
      "grade": "F",
      "rated": true,
      "reason": "Looks better than it is: most unclaimed prize money is likely on tickets already sold but not yet claimed (claim lag).",
      "remaining_tickets_min": 87840,
      "remaining_tickets_max": 88800,
      "ev_ratio_min": 1.544662,
      "ev_ratio_max": 1.561544,
      "ev_scenarios": [
        {
          "assumed_claimed_share": 0.5,
          "ev_ratio": 0.776529
        },
        {
          "assumed_claimed_share": 0.8,
          "ev_ratio": 0.310611
        },
        {
          "assumed_claimed_share": 0.95,
          "ev_ratio": 0.077653
        }
      ],
      "overall_odds_launch": 2.84
    },
    {
      "game_no": 632,
      "name": "CASH DOUBLE DOUBLER",
      "price": 10.0,
      "percent_unsold": 9.2,
      "total_unclaimed": 1073970.0,
      "top_prizes": [
        {
          "level": 5000,
          "remaining": 1
        },
        {
          "level": 1000,
          "remaining": 61
        },
        {
          "level": 500,
          "remaining": 182
        }
      ],
      "print_run": 1320000,
      "remaining_tickets": 121440,
      "ev_per_ticket": 8.843626,
      "ev_ratio": 0.884363,
      "ev_ratio_adjusted": null,
      "relative_score": 116735.869565,
      "top_prize_odds_now": null,
      "dead_game": true,
      "flags": [
        "anomaly_candidate"
      ],
      "confidence": "medium",
      "value_score": null,
      "grade": null,
      "rated": false,
      "reason": "Top prize already claimed \u2014 the biggest advertised win can no longer be won.",
      "remaining_tickets_min": 120780,
      "remaining_tickets_max": 122100,
      "ev_ratio_min": 0.879582,
      "ev_ratio_max": 0.889195,
      "ev_scenarios": [
        {
          "assumed_claimed_share": 0.5,
          "ev_ratio": 0.442182
        },
        {
          "assumed_claimed_share": 0.8,
          "ev_ratio": 0.176873
        },
        {
          "assumed_claimed_share": 0.95,
          "ev_ratio": 0.044218
        }
      ],
      "overall_odds_launch": 3.41
    },
    {
      "game_no": 638,
      "name": "TIC TAC MULTIPLIER",
      "price": 2.0,
      "percent_unsold": 0.3,
      "total_unclaimed": 122602.0,
      "top_prizes": [
        {
          "level": 10000,
          "remaining": 1
        },
        {
          "level": 500,
          "remaining": 4
        }
      ],
      "print_run": 840000,
      "remaining_tickets": 2520,
      "ev_per_ticket": 48.651587,
      "ev_ratio": 24.325794,
      "ev_ratio_adjusted": null,
      "relative_score": 408673.333333,
      "top_prize_odds_now": 2520.0,
      "dead_game": false,
      "flags": [
        "anomaly_candidate",
        "ev_out_of_range",
        "low_inventory"
      ],
      "confidence": "low",
      "value_score": 40,
      "grade": "F",
      "rated": true,
      "reason": "Looks better than it is: most unclaimed prize money is likely on tickets already sold but not yet claimed (claim lag).",
      "remaining_tickets_min": 2100,
      "remaining_tickets_max": 2940,
      "ev_ratio_min": 20.85068,
      "ev_ratio_max": 29.190952,
      "ev_scenarios": [
        {
          "assumed_claimed_share": 0.5,
          "ev_ratio": 12.162897
        },
        {
          "assumed_claimed_share": 0.8,
          "ev_ratio": 4.865159
        },
        {
          "assumed_claimed_share": 0.95,
          "ev_ratio": 1.21629
        }
      ],
      "overall_odds_launch": 4.27
    },
    {
      "game_no": 647,
      "name": "MAINE CROSSWORD",
      "price": 3.0,
      "percent_unsold": 7.1,
      "total_unclaimed": 1583796.0,
      "top_prizes": [
        {
          "level": 30000,
          "remaining": 4
        },
        {
          "level": 1000,
          "remaining": 14
        }
      ],
      "print_run": 5400000,
      "remaining_tickets": 383400,
      "ev_per_ticket": 4.130923,
      "ev_ratio": 1.376974,
      "ev_ratio_adjusted": null,
      "relative_score": 223069.859155,
      "top_prize_odds_now": 95850.0,
      "dead_game": false,
      "flags": [
        "anomaly_candidate"
      ],
      "confidence": "medium",
      "value_score": 95,
      "grade": "A",
      "rated": true,
      "reason": "Inventory is thinning; the expected-value estimate carries moderate uncertainty.",
      "remaining_tickets_min": 380700,
      "remaining_tickets_max": 386100,
      "ev_ratio_min": 1.367345,
      "ev_ratio_max": 1.38674,
      "ev_scenarios": [
        {
          "assumed_claimed_share": 0.5,
          "ev_ratio": 0.688487
        },
        {
          "assumed_claimed_share": 0.8,
          "ev_ratio": 0.275395
        },
        {
          "assumed_claimed_share": 0.95,
          "ev_ratio": 0.068849
        }
      ],
      "overall_odds_launch": 3.32
    },
    {
      "game_no": 648,
      "name": "DRAGONFLY DOLLARS",
      "price": 3.0,
      "percent_unsold": 28.8,
      "total_unclaimed": 806331.0,
      "top_prizes": [
        {
          "level": 30000,
          "remaining": 1
        },
        {
          "level": 1000,
          "remaining": 5
        },
        {
          "level": 500,
          "remaining": 8
        }
      ],
      "print_run": null,
      "remaining_tickets": null,
      "ev_per_ticket": null,
      "ev_ratio": null,
      "ev_ratio_adjusted": null,
      "relative_score": 27997.604167,
      "top_prize_odds_now": null,
      "dead_game": false,
      "flags": [
        "no_print_run"
      ],
      "confidence": "low",
      "value_score": null,
      "grade": null,
      "rated": false,
      "reason": "Print run unknown \u2014 expected value can't be computed; ranked by the relative unclaimed-money signal only.",
      "remaining_tickets_min": null,
      "remaining_tickets_max": null,
      "ev_ratio_min": null,
      "ev_ratio_max": null,
      "ev_scenarios": null,
      "overall_odds_launch": null
    },
    {
      "game_no": 651,
      "name": "MONEY CRAZE",
      "price": 10.0,
      "percent_unsold": 0.0,
      "total_unclaimed": 162675.0,
      "top_prizes": [
        {
          "level": 1000,
          "remaining": 5
        },
        {
          "level": 500,
          "remaining": 8
        }
      ],
      "print_run": 1200000,
      "remaining_tickets": 0,
      "ev_per_ticket": null,
      "ev_ratio": null,
      "ev_ratio_adjusted": null,
      "relative_score": null,
      "top_prize_odds_now": null,
      "dead_game": true,
      "flags": [
        "sold_out"
      ],
      "confidence": "low",
      "value_score": null,
      "grade": null,
      "rated": false,
      "reason": "Top prize already claimed \u2014 the biggest advertised win can no longer be won.",
      "remaining_tickets_min": null,
      "remaining_tickets_max": null,
      "ev_ratio_min": null,
      "ev_ratio_max": null,
      "ev_scenarios": null,
      "overall_odds_launch": 3.36
    },
    {
      "game_no": 654,
      "name": "MONEY TO GO!",
      "price": 5.0,
      "percent_unsold": 5.2,
      "total_unclaimed": 261235.0,
      "top_prizes": [
        {
          "level": 10000,
          "remaining": 1
        },
        {
          "level": 500,
          "remaining": 35
        }
      ],
      "print_run": 960000,
      "remaining_tickets": 49920,
      "ev_per_ticket": 5.233073,
      "ev_ratio": 1.046615,
      "ev_ratio_adjusted": null,
      "relative_score": 50237.5,
      "top_prize_odds_now": null,
      "dead_game": true,
      "flags": [
        "anomaly_candidate"
      ],
      "confidence": "medium",
      "value_score": null,
      "grade": null,
      "rated": false,
      "reason": "Top prize already claimed \u2014 the biggest advertised win can no longer be won.",
      "remaining_tickets_min": 49440,
      "remaining_tickets_max": 50400,
      "ev_ratio_min": 1.036647,
      "ev_ratio_max": 1.056776,
      "ev_scenarios": [
        {
          "assumed_claimed_share": 0.5,
          "ev_ratio": 0.523308
        },
        {
          "assumed_claimed_share": 0.8,
          "ev_ratio": 0.209323
        },
        {
          "assumed_claimed_share": 0.95,
          "ev_ratio": 0.052331
        }
      ],
      "overall_odds_launch": 3.88
    },
    {
      "game_no": 655,
      "name": "MAINE MILLIONS",
      "price": 30.0,
      "percent_unsold": 8.8,
      "total_unclaimed": 6127840.0,
      "top_prizes": [
        {
          "level": 100000,
          "remaining": 2
        },
        {
          "level": 50000,
          "remaining": 1
        },
        {
          "level": 5000,
          "remaining": 7
        },
        {
          "level": 1000,
          "remaining": 174
        },
        {
          "level": 500,
          "remaining": 553
        }
      ],
      "print_run": 2600000,
      "remaining_tickets": 228800,
      "ev_per_ticket": 26.782517,
      "ev_ratio": 0.892751,
      "ev_ratio_adjusted": null,
      "relative_score": 696345.454545,
      "top_prize_odds_now": null,
      "dead_game": true,
      "flags": [
        "anomaly_candidate"
      ],
      "confidence": "medium",
      "value_score": null,
      "grade": null,
      "rated": false,
      "reason": "Top prize already claimed \u2014 the biggest advertised win can no longer be won.",
      "remaining_tickets_min": 227500,
      "remaining_tickets_max": 230100,
      "ev_ratio_min": 0.887707,
      "ev_ratio_max": 0.897852,
      "ev_scenarios": [
        {
          "assumed_claimed_share": 0.5,
          "ev_ratio": 0.446376
        },
        {
          "assumed_claimed_share": 0.8,
          "ev_ratio": 0.17855
        },
        {
          "assumed_claimed_share": 0.95,
          "ev_ratio": 0.044638
        }
      ],
      "overall_odds_launch": 2.65
    },
    {
      "game_no": 656,
      "name": "POWER SPOT",
      "price": 5.0,
      "percent_unsold": 25.6,
      "total_unclaimed": 1432935.0,
      "top_prizes": [
        {
          "level": 100000,
          "remaining": 1
        },
        {
          "level": 20000,
          "remaining": 3
        },
        {
          "level": 5000,
          "remaining": 1
        },
        {
          "level": 1000,
          "remaining": 22
        }
      ],
      "print_run": 1320000,
      "remaining_tickets": 337920,
      "ev_per_ticket": 4.240456,
      "ev_ratio": 0.848091,
      "ev_ratio_adjusted": null,
      "relative_score": 55974.023438,
      "top_prize_odds_now": 337920.0,
      "dead_game": false,
      "flags": [],
      "confidence": "high",
      "value_score": 59,
      "grade": "C",
      "rated": true,
      "reason": "Based on solid inventory data; the expected-value estimate is comparatively reliable.",
      "remaining_tickets_min": 337260,
      "remaining_tickets_max": 338580,
      "ev_ratio_min": 0.846438,
      "ev_ratio_max": 0.849751,
      "ev_scenarios": [
        {
          "assumed_claimed_share": 0.5,
          "ev_ratio": 0.424046
        },
        {
          "assumed_claimed_share": 0.8,
          "ev_ratio": 0.169618
        },
        {
          "assumed_claimed_share": 0.95,
          "ev_ratio": 0.042405
        }
      ],
      "overall_odds_launch": 3.82
    },
    {
      "game_no": 660,
      "name": "ULTIMATE BONUS PAYOUT",
      "price": 10.0,
      "percent_unsold": 4.9,
      "total_unclaimed": 566565.0,
      "top_prizes": [
        {
          "level": 5000,
          "remaining": 2
        },
        {
          "level": 1000,
          "remaining": 29
        },
        {
          "level": 500,
          "remaining": 63
        }
      ],
      "print_run": 1200000,
      "remaining_tickets": 58800,
      "ev_per_ticket": 9.635459,
      "ev_ratio": 0.963546,
      "ev_ratio_adjusted": null,
      "relative_score": 115625.510204,
      "top_prize_odds_now": null,
      "dead_game": true,
      "flags": [
        "anomaly_candidate",
        "low_inventory"
      ],
      "confidence": "low",
      "value_score": null,
      "grade": null,
      "rated": false,
      "reason": "Top prize already claimed \u2014 the biggest advertised win can no longer be won.",
      "remaining_tickets_min": 58200,
      "remaining_tickets_max": 59400,
      "ev_ratio_min": 0.953813,
      "ev_ratio_max": 0.973479,
      "ev_scenarios": [
        {
          "assumed_claimed_share": 0.5,
          "ev_ratio": 0.481773
        },
        {
          "assumed_claimed_share": 0.8,
          "ev_ratio": 0.192709
        },
        {
          "assumed_claimed_share": 0.95,
          "ev_ratio": 0.048177
        }
      ],
      "overall_odds_launch": 3.47
    },
    {
      "game_no": 661,
      "name": "$50,000 BANKROLL",
      "price": 20.0,
      "percent_unsold": 0.1,
      "total_unclaimed": 551030.0,
      "top_prizes": [
        {
          "level": 50000,
          "remaining": 1
        },
        {
          "level": 5000,
          "remaining": 2
        },
        {
          "level": 1000,
          "remaining": 40
        },
        {
          "level": 500,
          "remaining": 74
        }
      ],
      "print_run": 720000,
      "remaining_tickets": 720,
      "ev_per_ticket": 765.319444,
      "ev_ratio": 38.265972,
      "ev_ratio_adjusted": null,
      "relative_score": 5510300.0,
      "top_prize_odds_now": 720.0,
      "dead_game": false,
      "flags": [
        "anomaly_candidate",
        "ev_out_of_range",
        "low_inventory"
      ],
      "confidence": "low",
      "value_score": 40,
      "grade": "F",
      "rated": true,
      "reason": "Looks better than it is: most unclaimed prize money is likely on tickets already sold but not yet claimed (claim lag).",
      "remaining_tickets_min": 360,
      "remaining_tickets_max": 1080,
      "ev_ratio_min": 25.510648,
      "ev_ratio_max": 76.531944,
      "ev_scenarios": [
        {
          "assumed_claimed_share": 0.5,
          "ev_ratio": 19.132986
        },
        {
          "assumed_claimed_share": 0.8,
          "ev_ratio": 7.653194
        },
        {
          "assumed_claimed_share": 0.95,
          "ev_ratio": 1.913299
        }
      ],
      "overall_odds_launch": 2.81
    },
    {
      "game_no": 662,
      "name": "COUNT `EM UP",
      "price": 2.0,
      "percent_unsold": 12.4,
      "total_unclaimed": 312510.0,
      "top_prizes": [
        {
          "level": 15000,
          "remaining": 1
        },
        {
          "level": 1000,
          "remaining": 5
        }
      ],
      "print_run": 960000,
      "remaining_tickets": 119040,
      "ev_per_ticket": 2.625252,
      "ev_ratio": 1.312626,
      "ev_ratio_adjusted": null,
      "relative_score": 25202.419355,
      "top_prize_odds_now": 119040.0,
      "dead_game": false,
      "flags": [
        "anomaly_candidate"
      ],
      "confidence": "medium",
      "value_score": 89,
      "grade": "A",
      "rated": true,
      "reason": "Inventory is thinning; the expected-value estimate carries moderate uncertainty.",
      "remaining_tickets_min": 118560,
      "remaining_tickets_max": 119520,
      "ev_ratio_min": 1.307354,
      "ev_ratio_max": 1.31794,
      "ev_scenarios": [
        {
          "assumed_claimed_share": 0.5,
          "ev_ratio": 0.656313
        },
        {
          "assumed_claimed_share": 0.8,
          "ev_ratio": 0.262525
        },
        {
          "assumed_claimed_share": 0.95,
          "ev_ratio": 0.065631
        }
      ],
      "overall_odds_launch": 4.19
    },
    {
      "game_no": 663,
      "name": "9`S IN A LINE",
      "price": 5.0,
      "percent_unsold": 0.9,
      "total_unclaimed": 124235.0,
      "top_prizes": [
        {
          "level": 1000,
          "remaining": 2
        }
      ],
      "print_run": 1200000,
      "remaining_tickets": 10800,
      "ev_per_ticket": 11.503241,
      "ev_ratio": 2.300648,
      "ev_ratio_adjusted": null,
      "relative_score": 138038.888889,
      "top_prize_odds_now": null,
      "dead_game": true,
      "flags": [
        "anomaly_candidate",
        "ev_out_of_range",
        "low_inventory"
      ],
      "confidence": "low",
      "value_score": null,
      "grade": null,
      "rated": false,
      "reason": "Top prize already claimed \u2014 the biggest advertised win can no longer be won.",
      "remaining_tickets_min": 10200,
      "remaining_tickets_max": 11400,
      "ev_ratio_min": 2.179561,
      "ev_ratio_max": 2.43598,
      "ev_scenarios": [
        {
          "assumed_claimed_share": 0.5,
          "ev_ratio": 1.150324
        },
        {
          "assumed_claimed_share": 0.8,
          "ev_ratio": 0.46013
        },
        {
          "assumed_claimed_share": 0.95,
          "ev_ratio": 0.115032
        }
      ],
      "overall_odds_launch": 3.82
    },
    {
      "game_no": 664,
      "name": "$100,000 WINNING 7",
      "price": 5.0,
      "percent_unsold": 4.7,
      "total_unclaimed": 278950.0,
      "top_prizes": [
        {
          "level": 1000,
          "remaining": 2
        }
      ],
      "print_run": null,
      "remaining_tickets": null,
      "ev_per_ticket": null,
      "ev_ratio": null,
      "ev_ratio_adjusted": null,
      "relative_score": 59351.06383,
      "top_prize_odds_now": null,
      "dead_game": false,
      "flags": [
        "low_inventory",
        "no_print_run"
      ],
      "confidence": "low",
      "value_score": null,
      "grade": null,
      "rated": false,
      "reason": "Print run unknown \u2014 expected value can't be computed; ranked by the relative unclaimed-money signal only.",
      "remaining_tickets_min": null,
      "remaining_tickets_max": null,
      "ev_ratio_min": null,
      "ev_ratio_max": null,
      "ev_scenarios": null,
      "overall_odds_launch": null
    },
    {
      "game_no": 667,
      "name": "CASH BONANZA",
      "price": 20.0,
      "percent_unsold": 16.8,
      "total_unclaimed": 2804100.0,
      "top_prizes": [
        {
          "level": 50000,
          "remaining": 1
        },
        {
          "level": 20000,
          "remaining": 4
        },
        {
          "level": 10000,
          "remaining": 2
        },
        {
          "level": 5000,
          "remaining": 16
        },
        {
          "level": 1000,
          "remaining": 247
        },
        {
          "level": 500,
          "remaining": 420
        }
      ],
      "print_run": 960000,
      "remaining_tickets": 161280,
      "ev_per_ticket": 17.386533,
      "ev_ratio": 0.869327,
      "ev_ratio_adjusted": null,
      "relative_score": 166910.714286,
      "top_prize_odds_now": null,
      "dead_game": true,
      "flags": [
        "anomaly_candidate"
      ],
      "confidence": "high",
      "value_score": null,
      "grade": null,
      "rated": false,
      "reason": "Top prize already claimed \u2014 the biggest advertised win can no longer be won.",
      "remaining_tickets_min": 160800,
      "remaining_tickets_max": 161760,
      "ev_ratio_min": 0.866747,
      "ev_ratio_max": 0.871922,
      "ev_scenarios": [
        {
          "assumed_claimed_share": 0.5,
          "ev_ratio": 0.434664
        },
        {
          "assumed_claimed_share": 0.8,
          "ev_ratio": 0.173865
        },
        {
          "assumed_claimed_share": 0.95,
          "ev_ratio": 0.043466
        }
      ],
      "overall_odds_launch": 2.89
    },
    {
      "game_no": 668,
      "name": "CA$H CRU$H",
      "price": 1.0,
      "percent_unsold": 6.1,
      "total_unclaimed": 96381.0,
      "top_prizes": [
        {
          "level": 1000,
          "remaining": 5
        }
      ],
      "print_run": null,
      "remaining_tickets": null,
      "ev_per_ticket": null,
      "ev_ratio": null,
      "ev_ratio_adjusted": null,
      "relative_score": 15800.163934,
      "top_prize_odds_now": null,
      "dead_game": false,
      "flags": [
        "no_print_run"
      ],
      "confidence": "low",
      "value_score": null,
      "grade": null,
      "rated": false,
      "reason": "Print run unknown \u2014 expected value can't be computed; ranked by the relative unclaimed-money signal only.",
      "remaining_tickets_min": null,
      "remaining_tickets_max": null,
      "ev_ratio_min": null,
      "ev_ratio_max": null,
      "ev_scenarios": null,
      "overall_odds_launch": null
    },
    {
      "game_no": 669,
      "name": "WIN WIN WIN",
      "price": 2.0,
      "percent_unsold": 17.0,
      "total_unclaimed": 240044.0,
      "top_prizes": [
        {
          "level": 1000,
          "remaining": 4
        }
      ],
      "print_run": null,
      "remaining_tickets": null,
      "ev_per_ticket": null,
      "ev_ratio": null,
      "ev_ratio_adjusted": null,
      "relative_score": 14120.235294,
      "top_prize_odds_now": null,
      "dead_game": false,
      "flags": [
        "no_print_run"
      ],
      "confidence": "low",
      "value_score": null,
      "grade": null,
      "rated": false,
      "reason": "Print run unknown \u2014 expected value can't be computed; ranked by the relative unclaimed-money signal only.",
      "remaining_tickets_min": null,
      "remaining_tickets_max": null,
      "ev_ratio_min": null,
      "ev_ratio_max": null,
      "ev_scenarios": null,
      "overall_odds_launch": null
    },
    {
      "game_no": 670,
      "name": "SHOW ME THE BENJAMINS",
      "price": 5.0,
      "percent_unsold": 1.3,
      "total_unclaimed": 146085.0,
      "top_prizes": [
        {
          "level": 10000,
          "remaining": 2
        },
        {
          "level": 1000,
          "remaining": 3
        },
        {
          "level": 500,
          "remaining": 5
        }
      ],
      "print_run": 960000,
      "remaining_tickets": 12480,
      "ev_per_ticket": 11.705529,
      "ev_ratio": 2.341106,
      "ev_ratio_adjusted": null,
      "relative_score": 112373.076923,
      "top_prize_odds_now": null,
      "dead_game": true,
      "flags": [
        "anomaly_candidate",
        "ev_out_of_range",
        "low_inventory"
      ],
      "confidence": "low",
      "value_score": null,
      "grade": null,
      "rated": false,
      "reason": "Top prize already claimed \u2014 the biggest advertised win can no longer be won.",
      "remaining_tickets_min": 12000,
      "remaining_tickets_max": 12960,
      "ev_ratio_min": 2.254398,
      "ev_ratio_max": 2.43475,
      "ev_scenarios": [
        {
          "assumed_claimed_share": 0.5,
          "ev_ratio": 1.170553
        },
        {
          "assumed_claimed_share": 0.8,
          "ev_ratio": 0.468221
        },
        {
          "assumed_claimed_share": 0.95,
          "ev_ratio": 0.117055
        }
      ],
      "overall_odds_launch": 3.9
    },
    {
      "game_no": 671,
      "name": "$100,000 JACKPOT",
      "price": 5.0,
      "percent_unsold": 21.3,
      "total_unclaimed": 754530.0,
      "top_prizes": [
        {
          "level": 10000,
          "remaining": 2
        },
        {
          "level": 1000,
          "remaining": 28
        }
      ],
      "print_run": 960000,
      "remaining_tickets": 204480,
      "ev_per_ticket": 3.689994,
      "ev_ratio": 0.737999,
      "ev_ratio_adjusted": null,
      "relative_score": 35423.943662,
      "top_prize_odds_now": null,
      "dead_game": true,
      "flags": [],
      "confidence": "high",
      "value_score": null,
      "grade": null,
      "rated": false,
      "reason": "Top prize already claimed \u2014 the biggest advertised win can no longer be won.",
      "remaining_tickets_min": 204000,
      "remaining_tickets_max": 204960,
      "ev_ratio_min": 0.73627,
      "ev_ratio_max": 0.739735,
      "ev_scenarios": [
        {
          "assumed_claimed_share": 0.5,
          "ev_ratio": 0.369
        },
        {
          "assumed_claimed_share": 0.8,
          "ev_ratio": 0.1476
        },
        {
          "assumed_claimed_share": 0.95,
          "ev_ratio": 0.0369
        }
      ],
      "overall_odds_launch": 3.87
    },
    {
      "game_no": 673,
      "name": "PINBALL PAYOUT",
      "price": 2.0,
      "percent_unsold": 7.5,
      "total_unclaimed": 169766.0,
      "top_prizes": [
        {
          "level": 1000,
          "remaining": 1
        }
      ],
      "print_run": 960000,
      "remaining_tickets": 72000,
      "ev_per_ticket": 2.357861,
      "ev_ratio": 1.178931,
      "ev_ratio_adjusted": null,
      "relative_score": 22635.466667,
      "top_prize_odds_now": null,
      "dead_game": true,
      "flags": [
        "anomaly_candidate"
      ],
      "confidence": "medium",
      "value_score": null,
      "grade": null,
      "rated": false,
      "reason": "Top prize already claimed \u2014 the biggest advertised win can no longer be won.",
      "remaining_tickets_min": 71520,
      "remaining_tickets_max": 72480,
      "ev_ratio_min": 1.171123,
      "ev_ratio_max": 1.186843,
      "ev_scenarios": [
        {
          "assumed_claimed_share": 0.5,
          "ev_ratio": 0.589466
        },
        {
          "assumed_claimed_share": 0.8,
          "ev_ratio": 0.235786
        },
        {
          "assumed_claimed_share": 0.95,
          "ev_ratio": 0.058947
        }
      ],
      "overall_odds_launch": 4.16
    },
    {
      "game_no": 674,
      "name": "CASH TIMES 10",
      "price": 10.0,
      "percent_unsold": 13.1,
      "total_unclaimed": 1769510.0,
      "top_prizes": [
        {
          "level": 250000,
          "remaining": 1
        },
        {
          "level": 25000,
          "remaining": 2
        },
        {
          "level": 10000,
          "remaining": 2
        },
        {
          "level": 5000,
          "remaining": 5
        },
        {
          "level": 1000,
          "remaining": 44
        },
        {
          "level": 500,
          "remaining": 145
        }
      ],
      "print_run": 1200000,
      "remaining_tickets": 157200,
      "ev_per_ticket": 11.256425,
      "ev_ratio": 1.125642,
      "ev_ratio_adjusted": null,
      "relative_score": 135077.099237,
      "top_prize_odds_now": 157200.0,
      "dead_game": false,
      "flags": [
        "anomaly_candidate"
      ],
      "confidence": "medium",
      "value_score": 71,
      "grade": "B",
      "rated": true,
      "reason": "Inventory is thinning; the expected-value estimate carries moderate uncertainty.",
      "remaining_tickets_min": 156600,
      "remaining_tickets_max": 157800,
      "ev_ratio_min": 1.121362,
      "ev_ratio_max": 1.129955,
      "ev_scenarios": [
        {
          "assumed_claimed_share": 0.5,
          "ev_ratio": 0.562821
        },
        {
          "assumed_claimed_share": 0.8,
          "ev_ratio": 0.225128
        },
        {
          "assumed_claimed_share": 0.95,
          "ev_ratio": 0.056282
        }
      ],
      "overall_odds_launch": 3.39
    },
    {
      "game_no": 675,
      "name": "BASEBALL",
      "price": 2.0,
      "percent_unsold": 47.7,
      "total_unclaimed": 585871.0,
      "top_prizes": [
        {
          "level": 10000,
          "remaining": 2
        },
        {
          "level": 1000,
          "remaining": 9
        }
      ],
      "print_run": 840000,
      "remaining_tickets": 400680,
      "ev_per_ticket": 1.462192,
      "ev_ratio": 0.731096,
      "ev_ratio_adjusted": null,
      "relative_score": 12282.410901,
      "top_prize_odds_now": 200340.0,
      "dead_game": false,
      "flags": [],
      "confidence": "high",
      "value_score": 46,
      "grade": "D",
      "rated": true,
      "reason": "Based on solid inventory data; the expected-value estimate is comparatively reliable.",
      "remaining_tickets_min": 400260,
      "remaining_tickets_max": 401100,
      "ev_ratio_min": 0.73033,
      "ev_ratio_max": 0.731863,
      "ev_scenarios": [
        {
          "assumed_claimed_share": 0.5,
          "ev_ratio": 0.365548
        },
        {
          "assumed_claimed_share": 0.8,
          "ev_ratio": 0.146219
        },
        {
          "assumed_claimed_share": 0.95,
          "ev_ratio": 0.036555
        }
      ],
      "overall_odds_launch": 4.11
    },
    {
      "game_no": 676,
      "name": "CROSSWORD BONUS",
      "price": 5.0,
      "percent_unsold": 5.6,
      "total_unclaimed": 458865.0,
      "top_prizes": [
        {
          "level": 1000,
          "remaining": 5
        },
        {
          "level": 500,
          "remaining": 19
        }
      ],
      "print_run": 1560000,
      "remaining_tickets": 87360,
      "ev_per_ticket": 5.252576,
      "ev_ratio": 1.050515,
      "ev_ratio_adjusted": null,
      "relative_score": 81940.178571,
      "top_prize_odds_now": null,
      "dead_game": true,
      "flags": [
        "anomaly_candidate"
      ],
      "confidence": "medium",
      "value_score": null,
      "grade": null,
      "rated": false,
      "reason": "Top prize already claimed \u2014 the biggest advertised win can no longer be won.",
      "remaining_tickets_min": 86580,
      "remaining_tickets_max": 88140,
      "ev_ratio_min": 1.041219,
      "ev_ratio_max": 1.059979,
      "ev_scenarios": [
        {
          "assumed_claimed_share": 0.5,
          "ev_ratio": 0.525258
        },
        {
          "assumed_claimed_share": 0.8,
          "ev_ratio": 0.210103
        },
        {
          "assumed_claimed_share": 0.95,
          "ev_ratio": 0.052526
        }
      ],
      "overall_odds_launch": 3.52
    },
    {
      "game_no": 677,
      "name": "BLAZING BUCKS",
      "price": 10.0,
      "percent_unsold": 25.1,
      "total_unclaimed": 3004200.0,
      "top_prizes": [
        {
          "level": 250000,
          "remaining": 1
        },
        {
          "level": 10000,
          "remaining": 2
        },
        {
          "level": 5000,
          "remaining": 6
        },
        {
          "level": 1000,
          "remaining": 167
        },
        {
          "level": 500,
          "remaining": 527
        }
      ],
      "print_run": 1320000,
      "remaining_tickets": 331320,
      "ev_per_ticket": 9.067367,
      "ev_ratio": 0.906737,
      "ev_ratio_adjusted": null,
      "relative_score": 119689.243028,
      "top_prize_odds_now": 331320.0,
      "dead_game": false,
      "flags": [
        "anomaly_candidate"
      ],
      "confidence": "high",
      "value_score": 66,
      "grade": "B-",
      "rated": true,
      "reason": "Based on solid inventory data; the expected-value estimate is comparatively reliable.",
      "remaining_tickets_min": 330660,
      "remaining_tickets_max": 331980,
      "ev_ratio_min": 0.904934,
      "ev_ratio_max": 0.908547,
      "ev_scenarios": [
        {
          "assumed_claimed_share": 0.5,
          "ev_ratio": 0.453369
        },
        {
          "assumed_claimed_share": 0.8,
          "ev_ratio": 0.181347
        },
        {
          "assumed_claimed_share": 0.95,
          "ev_ratio": 0.045337
        }
      ],
      "overall_odds_launch": 3.41
    },
    {
      "game_no": 680,
      "name": "ACE IN THE HOLE",
      "price": 2.0,
      "percent_unsold": 10.0,
      "total_unclaimed": 223956.0,
      "top_prizes": [
        {
          "level": 1000,
          "remaining": 2
        }
      ],
      "print_run": 960000,
      "remaining_tickets": 96000,
      "ev_per_ticket": 2.332875,
      "ev_ratio": 1.166438,
      "ev_ratio_adjusted": null,
      "relative_score": 22395.6,
      "top_prize_odds_now": null,
      "dead_game": true,
      "flags": [
        "anomaly_candidate"
      ],
      "confidence": "medium",
      "value_score": null,
      "grade": null,
      "rated": false,
      "reason": "Top prize already claimed \u2014 the biggest advertised win can no longer be won.",
      "remaining_tickets_min": 95520,
      "remaining_tickets_max": 96480,
      "ev_ratio_min": 1.160634,
      "ev_ratio_max": 1.172299,
      "ev_scenarios": [
        {
          "assumed_claimed_share": 0.5,
          "ev_ratio": 0.583219
        },
        {
          "assumed_claimed_share": 0.8,
          "ev_ratio": 0.233288
        },
        {
          "assumed_claimed_share": 0.95,
          "ev_ratio": 0.058322
        }
      ],
      "overall_odds_launch": 4.18
    },
    {
      "game_no": 681,
      "name": "$100,000 STACKS OF CASH",
      "price": 5.0,
      "percent_unsold": 12.5,
      "total_unclaimed": 448925.0,
      "top_prizes": [
        {
          "level": 1000,
          "remaining": 12
        }
      ],
      "print_run": null,
      "remaining_tickets": null,
      "ev_per_ticket": null,
      "ev_ratio": null,
      "ev_ratio_adjusted": null,
      "relative_score": 35914.0,
      "top_prize_odds_now": null,
      "dead_game": false,
      "flags": [
        "no_print_run"
      ],
      "confidence": "low",
      "value_score": null,
      "grade": null,
      "rated": false,
      "reason": "Print run unknown \u2014 expected value can't be computed; ranked by the relative unclaimed-money signal only.",
      "remaining_tickets_min": null,
      "remaining_tickets_max": null,
      "ev_ratio_min": null,
      "ev_ratio_max": null,
      "ev_scenarios": null,
      "overall_odds_launch": null
    },
    {
      "game_no": 682,
      "name": "BIG MONEY SPECTACULAR",
      "price": 2.0,
      "percent_unsold": 60.5,
      "total_unclaimed": 940574.0,
      "top_prizes": [
        {
          "level": 10000,
          "remaining": 5
        },
        {
          "level": 1000,
          "remaining": 14
        }
      ],
      "print_run": 840000,
      "remaining_tickets": 508200,
      "ev_per_ticket": 1.850795,
      "ev_ratio": 0.925397,
      "ev_ratio_adjusted": null,
      "relative_score": 15546.677686,
      "top_prize_odds_now": 101640.0,
      "dead_game": false,
      "flags": [
        "anomaly_candidate"
      ],
      "confidence": "high",
      "value_score": 68,
      "grade": "B",
      "rated": true,
      "reason": "Based on solid inventory data; the expected-value estimate is comparatively reliable.",
      "remaining_tickets_min": 507780,
      "remaining_tickets_max": 508620,
      "ev_ratio_min": 0.924633,
      "ev_ratio_max": 0.926163,
      "ev_scenarios": [
        {
          "assumed_claimed_share": 0.5,
          "ev_ratio": 0.462699
        },
        {
          "assumed_claimed_share": 0.8,
          "ev_ratio": 0.185079
        },
        {
          "assumed_claimed_share": 0.95,
          "ev_ratio": 0.04627
        }
      ],
      "overall_odds_launch": 4.16
    },
    {
      "game_no": 683,
      "name": "LADY LUCK",
      "price": 5.0,
      "percent_unsold": 1.5,
      "total_unclaimed": 224015.0,
      "top_prizes": [
        {
          "level": 1000,
          "remaining": 1
        }
      ],
      "print_run": 1200000,
      "remaining_tickets": 18000,
      "ev_per_ticket": 12.445278,
      "ev_ratio": 2.489056,
      "ev_ratio_adjusted": null,
      "relative_score": 149343.333333,
      "top_prize_odds_now": null,
      "dead_game": true,
      "flags": [
        "anomaly_candidate",
        "ev_out_of_range",
        "low_inventory"
      ],
      "confidence": "low",
      "value_score": null,
      "grade": null,
      "rated": false,
      "reason": "Top prize already claimed \u2014 the biggest advertised win can no longer be won.",
      "remaining_tickets_min": 17400,
      "remaining_tickets_max": 18600,
      "ev_ratio_min": 2.408763,
      "ev_ratio_max": 2.574885,
      "ev_scenarios": [
        {
          "assumed_claimed_share": 0.5,
          "ev_ratio": 1.244528
        },
        {
          "assumed_claimed_share": 0.8,
          "ev_ratio": 0.497811
        },
        {
          "assumed_claimed_share": 0.95,
          "ev_ratio": 0.124453
        }
      ],
      "overall_odds_launch": 3.78
    },
    {
      "game_no": 684,
      "name": "WINNING STREAK",
      "price": 5.0,
      "percent_unsold": 14.0,
      "total_unclaimed": 627675.0,
      "top_prizes": [
        {
          "level": 2500,
          "remaining": 8
        },
        {
          "level": 1250,
          "remaining": 4
        },
        {
          "level": 500,
          "remaining": 74
        }
      ],
      "print_run": 1200000,
      "remaining_tickets": 168000,
      "ev_per_ticket": 3.736161,
      "ev_ratio": 0.747232,
      "ev_ratio_adjusted": null,
      "relative_score": 44833.928571,
      "top_prize_odds_now": null,
      "dead_game": true,
      "flags": [],
      "confidence": "medium",
      "value_score": null,
      "grade": null,
      "rated": false,
      "reason": "Top prize already claimed \u2014 the biggest advertised win can no longer be won.",
      "remaining_tickets_min": 167400,
      "remaining_tickets_max": 168600,
      "ev_ratio_min": 0.744573,
      "ev_ratio_max": 0.74991,
      "ev_scenarios": [
        {
          "assumed_claimed_share": 0.5,
          "ev_ratio": 0.373616
        },
        {
          "assumed_claimed_share": 0.8,
          "ev_ratio": 0.149446
        },
        {
          "assumed_claimed_share": 0.95,
          "ev_ratio": 0.037362
        }
      ],
      "overall_odds_launch": 3.76
    },
    {
      "game_no": 685,
      "name": "20X THE WIN",
      "price": 5.0,
      "percent_unsold": 13.3,
      "total_unclaimed": 1197620.0,
      "top_prizes": [
        {
          "level": 100000,
          "remaining": 2
        },
        {
          "level": 5000,
          "remaining": 5
        },
        {
          "level": 1000,
          "remaining": 21
        }
      ],
      "print_run": 1560000,
      "remaining_tickets": 207480,
      "ev_per_ticket": 5.772219,
      "ev_ratio": 1.154444,
      "ev_ratio_adjusted": null,
      "relative_score": 90046.616541,
      "top_prize_odds_now": 103740.0,
      "dead_game": false,
      "flags": [
        "anomaly_candidate"
      ],
      "confidence": "medium",
      "value_score": 74,
      "grade": "B",
      "rated": true,
      "reason": "Inventory is thinning; the expected-value estimate carries moderate uncertainty.",
      "remaining_tickets_min": 206700,
      "remaining_tickets_max": 208260,
      "ev_ratio_min": 1.15012,
      "ev_ratio_max": 1.1588,
      "ev_scenarios": [
        {
          "assumed_claimed_share": 0.5,
          "ev_ratio": 0.577222
        },
        {
          "assumed_claimed_share": 0.8,
          "ev_ratio": 0.230889
        },
        {
          "assumed_claimed_share": 0.95,
          "ev_ratio": 0.057722
        }
      ],
      "overall_odds_launch": 3.87
    },
    {
      "game_no": 686,
      "name": "25X THE WIN",
      "price": 10.0,
      "percent_unsold": 47.3,
      "total_unclaimed": 5616780.0,
      "top_prizes": [
        {
          "level": 250000,
          "remaining": 1
        },
        {
          "level": 10000,
          "remaining": 2
        },
        {
          "level": 5000,
          "remaining": 9
        },
        {
          "level": 1000,
          "remaining": 217
        },
        {
          "level": 500,
          "remaining": 222
        }
      ],
      "print_run": 1440000,
      "remaining_tickets": 681120,
      "ev_per_ticket": 8.246388,
      "ev_ratio": 0.824639,
      "ev_ratio_adjusted": null,
      "relative_score": 118747.991543,
      "top_prize_odds_now": 681120.0,
      "dead_game": false,
      "flags": [],
      "confidence": "high",
      "value_score": 57,
      "grade": "C",
      "rated": true,
      "reason": "Based on solid inventory data; the expected-value estimate is comparatively reliable.",
      "remaining_tickets_min": 680400,
      "remaining_tickets_max": 681840,
      "ev_ratio_min": 0.823768,
      "ev_ratio_max": 0.825511,
      "ev_scenarios": [
        {
          "assumed_claimed_share": 0.5,
          "ev_ratio": 0.41232
        },
        {
          "assumed_claimed_share": 0.8,
          "ev_ratio": 0.164928
        },
        {
          "assumed_claimed_share": 0.95,
          "ev_ratio": 0.041232
        }
      ],
      "overall_odds_launch": 3.36
    },
    {
      "game_no": 687,
      "name": "10X THE WIN",
      "price": 2.0,
      "percent_unsold": 22.3,
      "total_unclaimed": 691113.0,
      "top_prizes": [
        {
          "level": 20000,
          "remaining": 2
        },
        {
          "level": 1000,
          "remaining": 11
        }
      ],
      "print_run": 1560000,
      "remaining_tickets": 347880,
      "ev_per_ticket": 1.986642,
      "ev_ratio": 0.993321,
      "ev_ratio_adjusted": null,
      "relative_score": 30991.61435,
      "top_prize_odds_now": 173940.0,
      "dead_game": false,
      "flags": [
        "anomaly_candidate"
      ],
      "confidence": "high",
      "value_score": 75,
      "grade": "B+",
      "rated": true,
      "reason": "Based on solid inventory data; the expected-value estimate is comparatively reliable.",
      "remaining_tickets_min": 347100,
      "remaining_tickets_max": 348660,
      "ev_ratio_min": 0.991099,
      "ev_ratio_max": 0.995553,
      "ev_scenarios": [
        {
          "assumed_claimed_share": 0.5,
          "ev_ratio": 0.496661
        },
        {
          "assumed_claimed_share": 0.8,
          "ev_ratio": 0.198664
        },
        {
          "assumed_claimed_share": 0.95,
          "ev_ratio": 0.049666
        }
      ],
      "overall_odds_launch": 4.31
    },
    {
      "game_no": 689,
      "name": "DEUCE$ WILD POKER",
      "price": 5.0,
      "percent_unsold": 0.5,
      "total_unclaimed": 123140.0,
      "top_prizes": [
        {
          "level": 1000,
          "remaining": 2
        },
        {
          "level": 500,
          "remaining": 2
        }
      ],
      "print_run": null,
      "remaining_tickets": null,
      "ev_per_ticket": null,
      "ev_ratio": null,
      "ev_ratio_adjusted": null,
      "relative_score": 246280.0,
      "top_prize_odds_now": null,
      "dead_game": false,
      "flags": [
        "low_inventory",
        "no_print_run"
      ],
      "confidence": "low",
      "value_score": null,
      "grade": null,
      "rated": false,
      "reason": "Print run unknown \u2014 expected value can't be computed; ranked by the relative unclaimed-money signal only.",
      "remaining_tickets_min": null,
      "remaining_tickets_max": null,
      "ev_ratio_min": null,
      "ev_ratio_max": null,
      "ev_scenarios": null,
      "overall_odds_launch": null
    },
    {
      "game_no": 690,
      "name": "$",
      "price": 1.0,
      "percent_unsold": 1.0,
      "total_unclaimed": 90335.0,
      "top_prizes": [
        {
          "level": 2000,
          "remaining": 1
        }
      ],
      "print_run": 960000,
      "remaining_tickets": 9600,
      "ev_per_ticket": 9.409896,
      "ev_ratio": 9.409896,
      "ev_ratio_adjusted": null,
      "relative_score": 90335.0,
      "top_prize_odds_now": 9600.0,
      "dead_game": false,
      "flags": [
        "anomaly_candidate",
        "ev_out_of_range",
        "low_inventory"
      ],
      "confidence": "low",
      "value_score": 40,
      "grade": "F",
      "rated": true,
      "reason": "Looks better than it is: most unclaimed prize money is likely on tickets already sold but not yet claimed (claim lag).",
      "remaining_tickets_min": 9120,
      "remaining_tickets_max": 10080,
      "ev_ratio_min": 8.961806,
      "ev_ratio_max": 9.905154,
      "ev_scenarios": [
        {
          "assumed_claimed_share": 0.5,
          "ev_ratio": 4.704948
        },
        {
          "assumed_claimed_share": 0.8,
          "ev_ratio": 1.881979
        },
        {
          "assumed_claimed_share": 0.95,
          "ev_ratio": 0.470495
        }
      ],
      "overall_odds_launch": 4.47
    },
    {
      "game_no": 691,
      "name": "LUCKY DOG",
      "price": 2.0,
      "percent_unsold": 5.3,
      "total_unclaimed": 165628.0,
      "top_prizes": [
        {
          "level": 1000,
          "remaining": 1
        }
      ],
      "print_run": 960000,
      "remaining_tickets": 50880,
      "ev_per_ticket": 3.255267,
      "ev_ratio": 1.627634,
      "ev_ratio_adjusted": null,
      "relative_score": 31250.566038,
      "top_prize_odds_now": null,
      "dead_game": true,
      "flags": [
        "anomaly_candidate",
        "ev_out_of_range"
      ],
      "confidence": "low",
      "value_score": null,
      "grade": null,
      "rated": false,
      "reason": "Top prize already claimed \u2014 the biggest advertised win can no longer be won.",
      "remaining_tickets_min": 50400,
      "remaining_tickets_max": 51360,
      "ev_ratio_min": 1.612422,
      "ev_ratio_max": 1.643135,
      "ev_scenarios": [
        {
          "assumed_claimed_share": 0.5,
          "ev_ratio": 0.813817
        },
        {
          "assumed_claimed_share": 0.8,
          "ev_ratio": 0.325527
        },
        {
          "assumed_claimed_share": 0.95,
          "ev_ratio": 0.081382
        }
      ],
      "overall_odds_launch": 4.21
    },
    {
      "game_no": 692,
      "name": "MONEY VAULT MULTIPLIER",
      "price": 5.0,
      "percent_unsold": 39.7,
      "total_unclaimed": 2318970.0,
      "top_prizes": [
        {
          "level": 100000,
          "remaining": 2
        },
        {
          "level": 10000,
          "remaining": 8
        },
        {
          "level": 1000,
          "remaining": 29
        },
        {
          "level": 500,
          "remaining": 133
        }
      ],
      "print_run": 1320000,
      "remaining_tickets": 524040,
      "ev_per_ticket": 4.425177,
      "ev_ratio": 0.885035,
      "ev_ratio_adjusted": null,
      "relative_score": 58412.342569,
      "top_prize_odds_now": 262020.0,
      "dead_game": false,
      "flags": [
        "anomaly_candidate"
      ],
      "confidence": "high",
      "value_score": 63,
      "grade": "B-",
      "rated": true,
      "reason": "Based on solid inventory data; the expected-value estimate is comparatively reliable.",
      "remaining_tickets_min": 523380,
      "remaining_tickets_max": 524700,
      "ev_ratio_min": 0.883922,
      "ev_ratio_max": 0.886152,
      "ev_scenarios": [
        {
          "assumed_claimed_share": 0.5,
          "ev_ratio": 0.442518
        },
        {
          "assumed_claimed_share": 0.8,
          "ev_ratio": 0.177007
        },
        {
          "assumed_claimed_share": 0.95,
          "ev_ratio": 0.044252
        }
      ],
      "overall_odds_launch": 3.79
    },
    {
      "game_no": 693,
      "name": "JURASSIC PARK",
      "price": 10.0,
      "percent_unsold": 24.4,
      "total_unclaimed": 5272645.0,
      "top_prizes": [
        {
          "level": 250000,
          "remaining": 2
        },
        {
          "level": 25000,
          "remaining": 3
        },
        {
          "level": 10000,
          "remaining": 6
        },
        {
          "level": 5000,
          "remaining": 8
        },
        {
          "level": 1000,
          "remaining": 135
        },
        {
          "level": 500,
          "remaining": 484
        }
      ],
      "print_run": 1200000,
      "remaining_tickets": 292800,
      "ev_per_ticket": 18.007667,
      "ev_ratio": 1.800767,
      "ev_ratio_adjusted": null,
      "relative_score": 216092.008197,
      "top_prize_odds_now": 146400.0,
      "dead_game": false,
      "flags": [
        "anomaly_candidate",
        "ev_out_of_range"
      ],
      "confidence": "low",
      "value_score": 40,
      "grade": "F",
      "rated": true,
      "reason": "Looks better than it is: most unclaimed prize money is likely on tickets already sold but not yet claimed (claim lag).",
      "remaining_tickets_min": 292200,
      "remaining_tickets_max": 293400,
      "ev_ratio_min": 1.797084,
      "ev_ratio_max": 1.804464,
      "ev_scenarios": [
        {
          "assumed_claimed_share": 0.5,
          "ev_ratio": 0.900384
        },
        {
          "assumed_claimed_share": 0.8,
          "ev_ratio": 0.360153
        },
        {
          "assumed_claimed_share": 0.95,
          "ev_ratio": 0.090038
        }
      ],
      "overall_odds_launch": 3.36
    },
    {
      "game_no": 694,
      "name": "CA$H IN",
      "price": 1.0,
      "percent_unsold": 15.4,
      "total_unclaimed": 229372.0,
      "top_prizes": [
        {
          "level": 1000,
          "remaining": 3
        }
      ],
      "print_run": 960000,
      "remaining_tickets": 147840,
      "ev_per_ticket": 1.551488,
      "ev_ratio": 1.551488,
      "ev_ratio_adjusted": null,
      "relative_score": 14894.285714,
      "top_prize_odds_now": 49280.0,
      "dead_game": false,
      "flags": [
        "anomaly_candidate",
        "ev_out_of_range"
      ],
      "confidence": "low",
      "value_score": 40,
      "grade": "F",
      "rated": true,
      "reason": "Looks better than it is: most unclaimed prize money is likely on tickets already sold but not yet claimed (claim lag).",
      "remaining_tickets_min": 147360,
      "remaining_tickets_max": 148320,
      "ev_ratio_min": 1.546467,
      "ev_ratio_max": 1.556542,
      "ev_scenarios": [
        {
          "assumed_claimed_share": 0.5,
          "ev_ratio": 0.775744
        },
        {
          "assumed_claimed_share": 0.8,
          "ev_ratio": 0.310298
        },
        {
          "assumed_claimed_share": 0.95,
          "ev_ratio": 0.077574
        }
      ],
      "overall_odds_launch": 4.66
    },
    {
      "game_no": 695,
      "name": "CASH LINE BINGO",
      "price": 3.0,
      "percent_unsold": 10.6,
      "total_unclaimed": 511305.0,
      "top_prizes": [
        {
          "level": 30000,
          "remaining": 1
        },
        {
          "level": 1500,
          "remaining": 2
        }
      ],
      "print_run": 960000,
      "remaining_tickets": 101760,
      "ev_per_ticket": 5.024617,
      "ev_ratio": 1.674872,
      "ev_ratio_adjusted": null,
      "relative_score": 48236.320755,
      "top_prize_odds_now": 101760.0,
      "dead_game": false,
      "flags": [
        "anomaly_candidate",
        "ev_out_of_range"
      ],
      "confidence": "low",
      "value_score": 40,
      "grade": "F",
      "rated": true,
      "reason": "Looks better than it is: most unclaimed prize money is likely on tickets already sold but not yet claimed (claim lag).",
      "remaining_tickets_min": 101280,
      "remaining_tickets_max": 102240,
      "ev_ratio_min": 1.667009,
      "ev_ratio_max": 1.68281,
      "ev_scenarios": [
        {
          "assumed_claimed_share": 0.5,
          "ev_ratio": 0.837436
        },
        {
          "assumed_claimed_share": 0.8,
          "ev_ratio": 0.334974
        },
        {
          "assumed_claimed_share": 0.95,
          "ev_ratio": 0.083744
        }
      ],
      "overall_odds_launch": 3.4
    },
    {
      "game_no": 696,
      "name": "SKEE-BALL",
      "price": 3.0,
      "percent_unsold": 5.6,
      "total_unclaimed": 396490.0,
      "top_prizes": [
        {
          "level": 30000,
          "remaining": 1
        },
        {
          "level": 1000,
          "remaining": 2
        },
        {
          "level": 500,
          "remaining": 2
        }
      ],
      "print_run": 1200000,
      "remaining_tickets": 67200,
      "ev_per_ticket": 5.900149,
      "ev_ratio": 1.966716,
      "ev_ratio_adjusted": null,
      "relative_score": 70801.785714,
      "top_prize_odds_now": 67200.0,
      "dead_game": false,
      "flags": [
        "anomaly_candidate",
        "ev_out_of_range"
      ],
      "confidence": "low",
      "value_score": 40,
      "grade": "F",
      "rated": true,
      "reason": "Looks better than it is: most unclaimed prize money is likely on tickets already sold but not yet claimed (claim lag).",
      "remaining_tickets_min": 66600,
      "remaining_tickets_max": 67800,
      "ev_ratio_min": 1.949312,
      "ev_ratio_max": 1.984434,
      "ev_scenarios": [
        {
          "assumed_claimed_share": 0.5,
          "ev_ratio": 0.983358
        },
        {
          "assumed_claimed_share": 0.8,
          "ev_ratio": 0.393343
        },
        {
          "assumed_claimed_share": 0.95,
          "ev_ratio": 0.098336
        }
      ],
      "overall_odds_launch": 3.43
    },
    {
      "game_no": 697,
      "name": "PATRIOTS",
      "price": 5.0,
      "percent_unsold": 28.7,
      "total_unclaimed": 1099925.0,
      "top_prizes": [
        {
          "level": 100000,
          "remaining": 1
        },
        {
          "level": 20000,
          "remaining": 2
        },
        {
          "level": 1000,
          "remaining": 9
        }
      ],
      "print_run": null,
      "remaining_tickets": null,
      "ev_per_ticket": null,
      "ev_ratio": null,
      "ev_ratio_adjusted": null,
      "relative_score": 38324.912892,
      "top_prize_odds_now": null,
      "dead_game": false,
      "flags": [
        "no_print_run"
      ],
      "confidence": "low",
      "value_score": null,
      "grade": null,
      "rated": false,
      "reason": "Print run unknown \u2014 expected value can't be computed; ranked by the relative unclaimed-money signal only.",
      "remaining_tickets_min": null,
      "remaining_tickets_max": null,
      "ev_ratio_min": null,
      "ev_ratio_max": null,
      "ev_scenarios": null,
      "overall_odds_launch": null
    },
    {
      "game_no": 699,
      "name": "LEAP FOR LOOT",
      "price": 3.0,
      "percent_unsold": 22.9,
      "total_unclaimed": 828099.0,
      "top_prizes": [
        {
          "level": 30000,
          "remaining": 1
        },
        {
          "level": 1000,
          "remaining": 3
        },
        {
          "level": 500,
          "remaining": 6
        }
      ],
      "print_run": 1200000,
      "remaining_tickets": 274800,
      "ev_per_ticket": 3.013461,
      "ev_ratio": 1.004487,
      "ev_ratio_adjusted": null,
      "relative_score": 36161.528384,
      "top_prize_odds_now": 274800.0,
      "dead_game": false,
      "flags": [
        "anomaly_candidate"
      ],
      "confidence": "high",
      "value_score": 77,
      "grade": "B+",
      "rated": true,
      "reason": "Based on solid inventory data; the expected-value estimate is comparatively reliable.",
      "remaining_tickets_min": 274200,
      "remaining_tickets_max": 275400,
      "ev_ratio_min": 1.002298,
      "ev_ratio_max": 1.006685,
      "ev_scenarios": [
        {
          "assumed_claimed_share": 0.5,
          "ev_ratio": 0.502244
        },
        {
          "assumed_claimed_share": 0.8,
          "ev_ratio": 0.200897
        },
        {
          "assumed_claimed_share": 0.95,
          "ev_ratio": 0.050224
        }
      ],
      "overall_odds_launch": 3.37
    },
    {
      "game_no": 702,
      "name": "HOLIDAY $500S",
      "price": 5.0,
      "percent_unsold": 0.4,
      "total_unclaimed": 164870.0,
      "top_prizes": [
        {
          "level": 500,
          "remaining": 36
        }
      ],
      "print_run": 960000,
      "remaining_tickets": 3840,
      "ev_per_ticket": 42.934896,
      "ev_ratio": 8.586979,
      "ev_ratio_adjusted": null,
      "relative_score": 412175.0,
      "top_prize_odds_now": 106.666667,
      "dead_game": false,
      "flags": [
        "anomaly_candidate",
        "ev_out_of_range",
        "low_inventory"
      ],
      "confidence": "low",
      "value_score": 40,
      "grade": "F",
      "rated": true,
      "reason": "Looks better than it is: most unclaimed prize money is likely on tickets already sold but not yet claimed (claim lag).",
      "remaining_tickets_min": 3360,
      "remaining_tickets_max": 4320,
      "ev_ratio_min": 7.63287,
      "ev_ratio_max": 9.81369,
      "ev_scenarios": [
        {
          "assumed_claimed_share": 0.5,
          "ev_ratio": 4.29349
        },
        {
          "assumed_claimed_share": 0.8,
          "ev_ratio": 1.717396
        },
        {
          "assumed_claimed_share": 0.95,
          "ev_ratio": 0.429349
        }
      ],
      "overall_odds_launch": 3.56
    },
    {
      "game_no": 703,
      "name": "HOLIDAY $1,000S",
      "price": 10.0,
      "percent_unsold": 19.4,
      "total_unclaimed": 1298780.0,
      "top_prizes": [
        {
          "level": 1000,
          "remaining": 459
        },
        {
          "level": 500,
          "remaining": 103
        }
      ],
      "print_run": 360000,
      "remaining_tickets": 69840,
      "ev_per_ticket": 18.596506,
      "ev_ratio": 1.859651,
      "ev_ratio_adjusted": null,
      "relative_score": 66947.42268,
      "top_prize_odds_now": 152.156863,
      "dead_game": false,
      "flags": [
        "anomaly_candidate",
        "ev_out_of_range"
      ],
      "confidence": "low",
      "value_score": 40,
      "grade": "F",
      "rated": true,
      "reason": "Looks better than it is: most unclaimed prize money is likely on tickets already sold but not yet claimed (claim lag).",
      "remaining_tickets_min": 69660,
      "remaining_tickets_max": 70020,
      "ev_ratio_min": 1.85487,
      "ev_ratio_max": 1.864456,
      "ev_scenarios": [
        {
          "assumed_claimed_share": 0.5,
          "ev_ratio": 0.929826
        },
        {
          "assumed_claimed_share": 0.8,
          "ev_ratio": 0.37193
        },
        {
          "assumed_claimed_share": 0.95,
          "ev_ratio": 0.092983
        }
      ],
      "overall_odds_launch": 3.63
    },
    {
      "game_no": 704,
      "name": "SILVER 7S",
      "price": 5.0,
      "percent_unsold": 12.0,
      "total_unclaimed": 642000.0,
      "top_prizes": [
        {
          "level": 10000,
          "remaining": 1
        },
        {
          "level": 1000,
          "remaining": 6
        }
      ],
      "print_run": 1200000,
      "remaining_tickets": 144000,
      "ev_per_ticket": 4.458333,
      "ev_ratio": 0.891667,
      "ev_ratio_adjusted": null,
      "relative_score": 53500.0,
      "top_prize_odds_now": null,
      "dead_game": true,
      "flags": [
        "anomaly_candidate"
      ],
      "confidence": "medium",
      "value_score": null,
      "grade": null,
      "rated": false,
      "reason": "Top prize already claimed \u2014 the biggest advertised win can no longer be won.",
      "remaining_tickets_min": 143400,
      "remaining_tickets_max": 144600,
      "ev_ratio_min": 0.887967,
      "ev_ratio_max": 0.895397,
      "ev_scenarios": [
        {
          "assumed_claimed_share": 0.5,
          "ev_ratio": 0.445834
        },
        {
          "assumed_claimed_share": 0.8,
          "ev_ratio": 0.178333
        },
        {
          "assumed_claimed_share": 0.95,
          "ev_ratio": 0.044583
        }
      ],
      "overall_odds_launch": 3.79
    },
    {
      "game_no": 705,
      "name": "ALL THE MONEY",
      "price": 2.0,
      "percent_unsold": 45.7,
      "total_unclaimed": 762557.0,
      "top_prizes": [
        {
          "level": 10000,
          "remaining": 5
        },
        {
          "level": 1000,
          "remaining": 19
        }
      ],
      "print_run": 840000,
      "remaining_tickets": 383880,
      "ev_per_ticket": 1.986446,
      "ev_ratio": 0.993223,
      "ev_ratio_adjusted": null,
      "relative_score": 16686.148796,
      "top_prize_odds_now": 76776.0,
      "dead_game": false,
      "flags": [
        "anomaly_candidate"
      ],
      "confidence": "high",
      "value_score": 75,
      "grade": "B+",
      "rated": true,
      "reason": "Based on solid inventory data; the expected-value estimate is comparatively reliable.",
      "remaining_tickets_min": 383460,
      "remaining_tickets_max": 384300,
      "ev_ratio_min": 0.992138,
      "ev_ratio_max": 0.994311,
      "ev_scenarios": [
        {
          "assumed_claimed_share": 0.5,
          "ev_ratio": 0.496612
        },
        {
          "assumed_claimed_share": 0.8,
          "ev_ratio": 0.198645
        },
        {
          "assumed_claimed_share": 0.95,
          "ev_ratio": 0.049661
        }
      ],
      "overall_odds_launch": 4.17
    },
    {
      "game_no": 706,
      "name": "DOUBLE YOUR DOLLARS",
      "price": 5.0,
      "percent_unsold": 0.0,
      "total_unclaimed": 358260.0,
      "top_prizes": [
        {
          "level": 100000,
          "remaining": 1
        },
        {
          "level": 10000,
          "remaining": 1
        },
        {
          "level": 1000,
          "remaining": 1
        }
      ],
      "print_run": 960000,
      "remaining_tickets": 0,
      "ev_per_ticket": null,
      "ev_ratio": null,
      "ev_ratio_adjusted": null,
      "relative_score": null,
      "top_prize_odds_now": null,
      "dead_game": false,
      "flags": [
        "sold_out"
      ],
      "confidence": "low",
      "value_score": null,
      "grade": null,
      "rated": false,
      "reason": "Reported 0% unsold \u2014 effectively sold out; there is nothing left to buy.",
      "remaining_tickets_min": null,
      "remaining_tickets_max": null,
      "ev_ratio_min": null,
      "ev_ratio_max": null,
      "ev_scenarios": null,
      "overall_odds_launch": 3.83
    },
    {
      "game_no": 707,
      "name": "$60,000 CASHWORD",
      "price": 5.0,
      "percent_unsold": 4.0,
      "total_unclaimed": 487275.0,
      "top_prizes": [
        {
          "level": 1000,
          "remaining": 9
        },
        {
          "level": 500,
          "remaining": 15
        }
      ],
      "print_run": 1560000,
      "remaining_tickets": 62400,
      "ev_per_ticket": 7.808894,
      "ev_ratio": 1.561779,
      "ev_ratio_adjusted": null,
      "relative_score": 121818.75,
      "top_prize_odds_now": null,
      "dead_game": true,
      "flags": [
        "anomaly_candidate",
        "ev_out_of_range",
        "low_inventory"
      ],
      "confidence": "low",
      "value_score": null,
      "grade": null,
      "rated": false,
      "reason": "Top prize already claimed \u2014 the biggest advertised win can no longer be won.",
      "remaining_tickets_min": 61620,
      "remaining_tickets_max": 63180,
      "ev_ratio_min": 1.542498,
      "ev_ratio_max": 1.581548,
      "ev_scenarios": [
        {
          "assumed_claimed_share": 0.5,
          "ev_ratio": 0.78089
        },
        {
          "assumed_claimed_share": 0.8,
          "ev_ratio": 0.312356
        },
        {
          "assumed_claimed_share": 0.95,
          "ev_ratio": 0.078089
        }
      ],
      "overall_odds_launch": 3.52
    },
    {
      "game_no": 708,
      "name": "ELECTRIC 8`S",
      "price": 2.0,
      "percent_unsold": 30.4,
      "total_unclaimed": 576490.0,
      "top_prizes": [
        {
          "level": 8888,
          "remaining": 2
        },
        {
          "level": 1000,
          "remaining": 3
        }
      ],
      "print_run": 840000,
      "remaining_tickets": 255360,
      "ev_per_ticket": 2.257558,
      "ev_ratio": 1.128779,
      "ev_ratio_adjusted": null,
      "relative_score": 18963.486842,
      "top_prize_odds_now": 127680.0,
      "dead_game": false,
      "flags": [
        "anomaly_candidate"
      ],
      "confidence": "high",
      "value_score": 90,
      "grade": "A",
      "rated": true,
      "reason": "Based on solid inventory data; the expected-value estimate is comparatively reliable.",
      "remaining_tickets_min": 254940,
      "remaining_tickets_max": 255780,
      "ev_ratio_min": 1.126925,
      "ev_ratio_max": 1.130639,
      "ev_scenarios": [
        {
          "assumed_claimed_share": 0.5,
          "ev_ratio": 0.56439
        },
        {
          "assumed_claimed_share": 0.8,
          "ev_ratio": 0.225756
        },
        {
          "assumed_claimed_share": 0.95,
          "ev_ratio": 0.056439
        }
      ],
      "overall_odds_launch": 4.22
    },
    {
      "game_no": 709,
      "name": "CA$H BLA$T",
      "price": 5.0,
      "percent_unsold": 22.7,
      "total_unclaimed": 1129085.0,
      "top_prizes": [
        {
          "level": 100000,
          "remaining": 1
        },
        {
          "level": 20000,
          "remaining": 2
        },
        {
          "level": 1000,
          "remaining": 3
        },
        {
          "level": 500,
          "remaining": 17
        }
      ],
      "print_run": 960000,
      "remaining_tickets": 217920,
      "ev_per_ticket": 5.18119,
      "ev_ratio": 1.036238,
      "ev_ratio_adjusted": null,
      "relative_score": 49739.427313,
      "top_prize_odds_now": 217920.0,
      "dead_game": false,
      "flags": [
        "anomaly_candidate"
      ],
      "confidence": "high",
      "value_score": 80,
      "grade": "A-",
      "rated": true,
      "reason": "Based on solid inventory data; the expected-value estimate is comparatively reliable.",
      "remaining_tickets_min": 217440,
      "remaining_tickets_max": 218400,
      "ev_ratio_min": 1.033961,
      "ev_ratio_max": 1.038526,
      "ev_scenarios": [
        {
          "assumed_claimed_share": 0.5,
          "ev_ratio": 0.518119
        },
        {
          "assumed_claimed_share": 0.8,
          "ev_ratio": 0.207248
        },
        {
          "assumed_claimed_share": 0.95,
          "ev_ratio": 0.051812
        }
      ],
      "overall_odds_launch": 3.87
    },
    {
      "game_no": 710,
      "name": "$500 CA$H!",
      "price": 5.0,
      "percent_unsold": 0.1,
      "total_unclaimed": 74330.0,
      "top_prizes": [
        {
          "level": 500,
          "remaining": 15
        }
      ],
      "print_run": null,
      "remaining_tickets": null,
      "ev_per_ticket": null,
      "ev_ratio": null,
      "ev_ratio_adjusted": null,
      "relative_score": 743300.0,
      "top_prize_odds_now": null,
      "dead_game": false,
      "flags": [
        "low_inventory",
        "no_print_run"
      ],
      "confidence": "low",
      "value_score": null,
      "grade": null,
      "rated": false,
      "reason": "Print run unknown \u2014 expected value can't be computed; ranked by the relative unclaimed-money signal only.",
      "remaining_tickets_min": null,
      "remaining_tickets_max": null,
      "ev_ratio_min": null,
      "ev_ratio_max": null,
      "ev_scenarios": null,
      "overall_odds_launch": null
    },
    {
      "game_no": 711,
      "name": "HAMILTON",
      "price": 10.0,
      "percent_unsold": 33.0,
      "total_unclaimed": 3585940.0,
      "top_prizes": [
        {
          "level": 250000,
          "remaining": 1
        },
        {
          "level": 25000,
          "remaining": 2
        },
        {
          "level": 10000,
          "remaining": 3
        },
        {
          "level": 2500,
          "remaining": 8
        },
        {
          "level": 1000,
          "remaining": 103
        },
        {
          "level": 500,
          "remaining": 375
        }
      ],
      "print_run": 1200000,
      "remaining_tickets": 396000,
      "ev_per_ticket": 9.055404,
      "ev_ratio": 0.90554,
      "ev_ratio_adjusted": null,
      "relative_score": 108664.848485,
      "top_prize_odds_now": 396000.0,
      "dead_game": false,
      "flags": [
        "anomaly_candidate"
      ],
      "confidence": "high",
      "value_score": 66,
      "grade": "B-",
      "rated": true,
      "reason": "Based on solid inventory data; the expected-value estimate is comparatively reliable.",
      "remaining_tickets_min": 395400,
      "remaining_tickets_max": 396600,
      "ev_ratio_min": 0.90417,
      "ev_ratio_max": 0.906915,
      "ev_scenarios": [
        {
          "assumed_claimed_share": 0.5,
          "ev_ratio": 0.45277
        },
        {
          "assumed_claimed_share": 0.8,
          "ev_ratio": 0.181108
        },
        {
          "assumed_claimed_share": 0.95,
          "ev_ratio": 0.045277
        }
      ],
      "overall_odds_launch": 3.39
    },
    {
      "game_no": 716,
      "name": "COLOR BLAST CROSSWORD",
      "price": 10.0,
      "percent_unsold": 84.1,
      "total_unclaimed": 12485870.0,
      "top_prizes": [
        {
          "level": 125000,
          "remaining": 4
        },
        {
          "level": 10000,
          "remaining": 14
        },
        {
          "level": 1000,
          "remaining": 40
        }
      ],
      "print_run": 1800000,
      "remaining_tickets": 1513800,
      "ev_per_ticket": 8.248031,
      "ev_ratio": 0.824803,
      "ev_ratio_adjusted": null,
      "relative_score": 148464.565993,
      "top_prize_odds_now": 378450.0,
      "dead_game": false,
      "flags": [],
      "confidence": "high",
      "value_score": 57,
      "grade": "C",
      "rated": true,
      "reason": "Based on solid inventory data; the expected-value estimate is comparatively reliable.",
      "remaining_tickets_min": 1512900,
      "remaining_tickets_max": 1514700,
      "ev_ratio_min": 0.824313,
      "ev_ratio_max": 0.825294,
      "ev_scenarios": [
        {
          "assumed_claimed_share": 0.5,
          "ev_ratio": 0.412402
        },
        {
          "assumed_claimed_share": 0.8,
          "ev_ratio": 0.164961
        },
        {
          "assumed_claimed_share": 0.95,
          "ev_ratio": 0.04124
        }
      ],
      "overall_odds_launch": 3.15
    },
    {
      "game_no": 717,
      "name": "HI OR LO",
      "price": 5.0,
      "percent_unsold": 42.2,
      "total_unclaimed": 1720565.0,
      "top_prizes": [
        {
          "level": 100000,
          "remaining": 1
        },
        {
          "level": 10000,
          "remaining": 3
        },
        {
          "level": 1000,
          "remaining": 54
        }
      ],
      "print_run": 960000,
      "remaining_tickets": 405120,
      "ev_per_ticket": 4.24705,
      "ev_ratio": 0.84941,
      "ev_ratio_adjusted": null,
      "relative_score": 40771.682464,
      "top_prize_odds_now": 405120.0,
      "dead_game": false,
      "flags": [],
      "confidence": "high",
      "value_score": 59,
      "grade": "C",
      "rated": true,
      "reason": "Based on solid inventory data; the expected-value estimate is comparatively reliable.",
      "remaining_tickets_min": 404640,
      "remaining_tickets_max": 405600,
      "ev_ratio_min": 0.848405,
      "ev_ratio_max": 0.850418,
      "ev_scenarios": [
        {
          "assumed_claimed_share": 0.5,
          "ev_ratio": 0.424705
        },
        {
          "assumed_claimed_share": 0.8,
          "ev_ratio": 0.169882
        },
        {
          "assumed_claimed_share": 0.95,
          "ev_ratio": 0.042471
        }
      ],
      "overall_odds_launch": 3.87
    },
    {
      "game_no": 718,
      "name": "$70 MILLION SUPREME",
      "price": 30.0,
      "percent_unsold": 70.2,
      "total_unclaimed": 56905300.0,
      "top_prizes": [
        {
          "level": 1000000,
          "remaining": 4
        },
        {
          "level": 100000,
          "remaining": 5
        },
        {
          "level": 50000,
          "remaining": 6
        },
        {
          "level": 10000,
          "remaining": 14
        },
        {
          "level": 5000,
          "remaining": 53
        },
        {
          "level": 1000,
          "remaining": 1286
        },
        {
          "level": 500,
          "remaining": 6128
        }
      ],
      "print_run": 3100000,
      "remaining_tickets": 2176200,
      "ev_per_ticket": 26.148929,
      "ev_ratio": 0.871631,
      "ev_ratio_adjusted": null,
      "relative_score": 810616.809117,
      "top_prize_odds_now": 544050.0,
      "dead_game": false,
      "flags": [
        "anomaly_candidate"
      ],
      "confidence": "high",
      "value_score": 62,
      "grade": "B-",
      "rated": true,
      "reason": "Based on solid inventory data; the expected-value estimate is comparatively reliable.",
      "remaining_tickets_min": 2174650,
      "remaining_tickets_max": 2177750,
      "ev_ratio_min": 0.871011,
      "ev_ratio_max": 0.872252,
      "ev_scenarios": [
        {
          "assumed_claimed_share": 0.5,
          "ev_ratio": 0.435816
        },
        {
          "assumed_claimed_share": 0.8,
          "ev_ratio": 0.174326
        },
        {
          "assumed_claimed_share": 0.95,
          "ev_ratio": 0.043582
        }
      ],
      "overall_odds_launch": 2.98
    },
    {
      "game_no": 720,
      "name": "CROSSWORD",
      "price": 5.0,
      "percent_unsold": 84.5,
      "total_unclaimed": 5328770.0,
      "top_prizes": [
        {
          "level": 60000,
          "remaining": 5
        },
        {
          "level": 10000,
          "remaining": 10
        },
        {
          "level": 1000,
          "remaining": 67
        },
        {
          "level": 500,
          "remaining": 297
        }
      ],
      "print_run": 1560000,
      "remaining_tickets": 1318200,
      "ev_per_ticket": 4.042459,
      "ev_ratio": 0.808492,
      "ev_ratio_adjusted": null,
      "relative_score": 63062.366864,
      "top_prize_odds_now": 263640.0,
      "dead_game": false,
      "flags": [],
      "confidence": "high",
      "value_score": 55,
      "grade": "C",
      "rated": true,
      "reason": "Based on solid inventory data; the expected-value estimate is comparatively reliable.",
      "remaining_tickets_min": 1317420,
      "remaining_tickets_max": 1318980,
      "ev_ratio_min": 0.808014,
      "ev_ratio_max": 0.808971,
      "ev_scenarios": [
        {
          "assumed_claimed_share": 0.5,
          "ev_ratio": 0.404246
        },
        {
          "assumed_claimed_share": 0.8,
          "ev_ratio": 0.161698
        },
        {
          "assumed_claimed_share": 0.95,
          "ev_ratio": 0.040425
        }
      ],
      "overall_odds_launch": 3.52
    },
    {
      "game_no": 723,
      "name": "RED HOT RICHES",
      "price": 5.0,
      "percent_unsold": 40.3,
      "total_unclaimed": 1727575.0,
      "top_prizes": [
        {
          "level": 100000,
          "remaining": 1
        },
        {
          "level": 10000,
          "remaining": 4
        },
        {
          "level": 1000,
          "remaining": 57
        }
      ],
      "print_run": 960000,
      "remaining_tickets": 386880,
      "ev_per_ticket": 4.465403,
      "ev_ratio": 0.893081,
      "ev_ratio_adjusted": null,
      "relative_score": 42867.866005,
      "top_prize_odds_now": 386880.0,
      "dead_game": false,
      "flags": [
        "anomaly_candidate"
      ],
      "confidence": "high",
      "value_score": 64,
      "grade": "B-",
      "rated": true,
      "reason": "Based on solid inventory data; the expected-value estimate is comparatively reliable.",
      "remaining_tickets_min": 386400,
      "remaining_tickets_max": 387360,
      "ev_ratio_min": 0.891974,
      "ev_ratio_max": 0.89419,
      "ev_scenarios": [
        {
          "assumed_claimed_share": 0.5,
          "ev_ratio": 0.446541
        },
        {
          "assumed_claimed_share": 0.8,
          "ev_ratio": 0.178616
        },
        {
          "assumed_claimed_share": 0.95,
          "ev_ratio": 0.044654
        }
      ],
      "overall_odds_launch": 3.87
    },
    {
      "game_no": 725,
      "name": "HIGH CARD POKER",
      "price": 5.0,
      "percent_unsold": 57.6,
      "total_unclaimed": 2408330.0,
      "top_prizes": [
        {
          "level": 100000,
          "remaining": 2
        },
        {
          "level": 5000,
          "remaining": 13
        },
        {
          "level": 1000,
          "remaining": 37
        },
        {
          "level": 500,
          "remaining": 119
        }
      ],
      "print_run": 960000,
      "remaining_tickets": 552960,
      "ev_per_ticket": 4.355342,
      "ev_ratio": 0.871068,
      "ev_ratio_adjusted": null,
      "relative_score": 41811.284722,
      "top_prize_odds_now": 276480.0,
      "dead_game": false,
      "flags": [
        "anomaly_candidate"
      ],
      "confidence": "high",
      "value_score": 62,
      "grade": "B-",
      "rated": true,
      "reason": "Based on solid inventory data; the expected-value estimate is comparatively reliable.",
      "remaining_tickets_min": 552480,
      "remaining_tickets_max": 553440,
      "ev_ratio_min": 0.870313,
      "ev_ratio_max": 0.871825,
      "ev_scenarios": [
        {
          "assumed_claimed_share": 0.5,
          "ev_ratio": 0.435534
        },
        {
          "assumed_claimed_share": 0.8,
          "ev_ratio": 0.174214
        },
        {
          "assumed_claimed_share": 0.95,
          "ev_ratio": 0.043553
        }
      ],
      "overall_odds_launch": 3.91
    },
    {
      "game_no": 729,
      "name": "7-11-21",
      "price": 1.0,
      "percent_unsold": 67.4,
      "total_unclaimed": 602264.0,
      "top_prizes": [
        {
          "level": 1000,
          "remaining": 11
        }
      ],
      "print_run": 960000,
      "remaining_tickets": 647040,
      "ev_per_ticket": 0.930799,
      "ev_ratio": 0.930799,
      "ev_ratio_adjusted": null,
      "relative_score": 8935.667656,
      "top_prize_odds_now": 58821.818182,
      "dead_game": false,
      "flags": [
        "anomaly_candidate"
      ],
      "confidence": "high",
      "value_score": 68,
      "grade": "B",
      "rated": true,
      "reason": "Based on solid inventory data; the expected-value estimate is comparatively reliable.",
      "remaining_tickets_min": 646560,
      "remaining_tickets_max": 647520,
      "ev_ratio_min": 0.930109,
      "ev_ratio_max": 0.93149,
      "ev_scenarios": [
        {
          "assumed_claimed_share": 0.5,
          "ev_ratio": 0.4654
        },
        {
          "assumed_claimed_share": 0.8,
          "ev_ratio": 0.18616
        },
        {
          "assumed_claimed_share": 0.95,
          "ev_ratio": 0.04654
        }
      ],
      "overall_odds_launch": 4.66
    },
    {
      "game_no": 730,
      "name": "GRAB A GRAND",
      "price": 1.0,
      "percent_unsold": 56.9,
      "total_unclaimed": 523246.0,
      "top_prizes": [
        {
          "level": 1000,
          "remaining": 12
        }
      ],
      "print_run": 960000,
      "remaining_tickets": 546240,
      "ev_per_ticket": 0.957905,
      "ev_ratio": 0.957905,
      "ev_ratio_adjusted": null,
      "relative_score": 9195.887522,
      "top_prize_odds_now": 45520.0,
      "dead_game": false,
      "flags": [
        "anomaly_candidate"
      ],
      "confidence": "high",
      "value_score": 71,
      "grade": "B",
      "rated": true,
      "reason": "Based on solid inventory data; the expected-value estimate is comparatively reliable.",
      "remaining_tickets_min": 545760,
      "remaining_tickets_max": 546720,
      "ev_ratio_min": 0.957064,
      "ev_ratio_max": 0.958747,
      "ev_scenarios": [
        {
          "assumed_claimed_share": 0.5,
          "ev_ratio": 0.478953
        },
        {
          "assumed_claimed_share": 0.8,
          "ev_ratio": 0.191581
        },
        {
          "assumed_claimed_share": 0.95,
          "ev_ratio": 0.047895
        }
      ],
      "overall_odds_launch": 4.43
    },
    {
      "game_no": 735,
      "name": "LOTERIA",
      "price": 3.0,
      "percent_unsold": 71.0,
      "total_unclaimed": 1548265.0,
      "top_prizes": [
        {
          "level": 30000,
          "remaining": 2
        },
        {
          "level": 500,
          "remaining": 11
        }
      ],
      "print_run": 840000,
      "remaining_tickets": 596400,
      "ev_per_ticket": 2.596018,
      "ev_ratio": 0.865339,
      "ev_ratio_adjusted": null,
      "relative_score": 21806.549296,
      "top_prize_odds_now": 298200.0,
      "dead_game": false,
      "flags": [
        "anomaly_candidate"
      ],
      "confidence": "high",
      "value_score": 61,
      "grade": "C",
      "rated": true,
      "reason": "Based on solid inventory data; the expected-value estimate is comparatively reliable.",
      "remaining_tickets_min": 595980,
      "remaining_tickets_max": 596820,
      "ev_ratio_min": 0.86473,
      "ev_ratio_max": 0.865949,
      "ev_scenarios": [
        {
          "assumed_claimed_share": 0.5,
          "ev_ratio": 0.43267
        },
        {
          "assumed_claimed_share": 0.8,
          "ev_ratio": 0.173068
        },
        {
          "assumed_claimed_share": 0.95,
          "ev_ratio": 0.043267
        }
      ],
      "overall_odds_launch": 3.51
    },
    {
      "game_no": 737,
      "name": "FIND $500!",
      "price": 5.0,
      "percent_unsold": 59.6,
      "total_unclaimed": 2780485.0,
      "top_prizes": [
        {
          "level": 500,
          "remaining": 1563
        }
      ],
      "print_run": 960000,
      "remaining_tickets": 572160,
      "ev_per_ticket": 4.859628,
      "ev_ratio": 0.971926,
      "ev_ratio_adjusted": null,
      "relative_score": 46652.432886,
      "top_prize_odds_now": 366.065259,
      "dead_game": false,
      "flags": [
        "anomaly_candidate"
      ],
      "confidence": "high",
      "value_score": 73,
      "grade": "B",
      "rated": true,
      "reason": "Based on solid inventory data; the expected-value estimate is comparatively reliable.",
      "remaining_tickets_min": 571680,
      "remaining_tickets_max": 572640,
      "ev_ratio_min": 0.971111,
      "ev_ratio_max": 0.972742,
      "ev_scenarios": [
        {
          "assumed_claimed_share": 0.5,
          "ev_ratio": 0.485963
        },
        {
          "assumed_claimed_share": 0.8,
          "ev_ratio": 0.194385
        },
        {
          "assumed_claimed_share": 0.95,
          "ev_ratio": 0.048596
        }
      ],
      "overall_odds_launch": 3.58
    }
  ]
}